{
        "id": 5310512,
        "text": "结局-荒野的呼号",
        "is_replay": 0, 
        "auto_start": false, 
        "start_trigger": true,  //立即触发
        "on":{   
            "rite_end": 5010024
        },
        "condition":{
            "counter.7000447>=":1, //改革
            "have.2000771.宰相":1, //芮尔是宰相
            "counter.7100003>=":30, //权势
        },
        "settlement": [    
        {
            "tips_resource":"", 
            "tips_text":"",
            "action":{     
                "over":240
            }
        }
    ]
} 