 {
        "id": 5000526,
        "name": "复仇的伊始",
        "text": "红烛暖帐，弦歌缠绕着美酒的醇香，一个女人将献祭自己所有的一切，化作一个甜蜜的陷阱，一座欲望的迷宫，一个永远不会回望的夜晚。",       
        "tips": "",
        "mapping_id":8001222,
        "once_new":0,
        "round_number": 3,
        "waiting_round":0,
        "waiting_round_end_action":[
        ],
        "method_settlement": "",
        "auto_begin": 1,
        "auto_result":0,
        "location": "宫廷:[2,6]", 
        "icon": "rite_4",  
        "tag_tips": [
        ],
        "tag_tips_up":{
        },
        "tips_text":[
            "安苏亚正在履行自己的承诺，而你能做的只有等待。"
        ],
        "open_conditions": [
        ],
        "random_text": {        
        },
        "random_text_up":{
        },
        "random_effect": {          
        },
        "settlement_prior": [
        ],                
        "settlement": [
            {
                "condition": {
                },
                "result_title":"",
                "result_text": "安苏亚派人传来消息。她成功了。苏丹的魔法戒指已在昨夜被她偷偷掉包，接下来的事就得靠你了。你必须在苏丹觉察异状之前出击，否则你很难再有这么好的机会。",
                "result": 
                {
                    "global_counter=7200167":1, //成就
                    "s2-equip":2000529,
                    "card":[2000281, "已拥有+1"]  //获得戒指,并添加已拥有标签
                },
                "action": {
                    "global_counter=7200249":1, //成就-苏丹的戒指
                    "event_on":5300157, //激活弑君仪式幕后
                    "event_on":5300050 //激活东窗事发幕后

                }
            }
        ],                
        "settlement_extre": [
        ],
        "cards_slot":
        {
            "s1":
            {
                "condition":
                {
                    
                    "is": 2000008           
                },
                "open_adsorb":1,
                "is_key":0,
                "is_empty":0,
                "is_enemy":0,
                "text":"安苏亚正在行动"
            },
            "s2":
            {
                "condition":
                {
                    "is": 2000024 
                },
                "open_adsorb":1,
                "is_key":0,
                "is_empty":0,
                "is_enemy":0,
                "text":"傲慢的君主"
            }
        }
    } 