 {
        "id": 5000116,
        "name": "追忆过去荣光",
        "text": "阅读可以提升自己，养成阅读的习惯吧",       
        "tips": "",
        "mapping_id":8001005,
        "once_new":0,
        "round_number": 0,
        "waiting_round":1,
        "waiting_round_end_action":[
        ],
        "method_settlement": "",
        "auto_begin": 0,
        "auto_result":0,
        "location": "自宅:[2,12]", 
        "icon": "rite_7", 
        "tag_tips": [
        ],
        "tag_tips_up":{
        },
        "tips_text":[
            "只有非贵族角色才可以阅读。"
        ],
        "open_conditions": [
        ],
        "random_text":{
        },
        "random_text_up":{
        },
        "settlement_prior": [
        ],                
        "settlement": [
            {
                "condition":
                {
                },
                "result_title":"",
                "result_text": "你的魅力和社交能力提升了",
                "result": 
                {   
                    "s1-已拥有":1,
                    "s1-正在阅读":1,
                    "s2+魅力":1,
                    "s2+社交":1,
                    "pop.5000116_01.s2": "妙啊！"                                
                },
                "action":
                {
                }
            }
        ],                
        "settlement_extre": [
            {
                "condition":
                {
                    "!s2.贵族":1
                },
                "result_title":"",
                "result_text": "[s2.name]成为了一名贵族。",
                "result": 
                {   
                    "s2+贵族":1,
                    "pop.5000116_02.s2": "我成贵族了？"                                
                },
                "action":
                {
                }
            }
        ],
        "cards_slot":
        {
            "s1":
                {
                    "condition": 
                    {
                        "type":"item",
                        "正在阅读":1,
                        "is":2000475                  
                    },
                    "open_adsorb":1,
                    "is_key":0,
                    "is_empty":0,
                    "is_enemy":1,
                    "text":"诗歌" 
                },
            "s2":
                {
                    "condition": 
                    {
                        "type":"char",
                        "!贵族":1,                       
                        "!动物":1,
                        "!怪物":1
                    },
                    "open_adsorb":0,
                    "is_key":0,
                    "is_empty":0,
                    "is_enemy":0,
                    "text":"非贵族的阅读者"
                }
        }
    } 