 {
        "id": 5001023,
        "name": "改朝换代",
        "text": "苏丹拥有军队，拥有强大的魔法戒指——并且他本人据说也是几乎无敌的战士。你当然需要强大的军队，宝剑与魔法来与之对抗，但终结旧王朝，创造新王朝的永远不是这些，而是思想。",       
        "tips": "",
        "once_new":0,
        "round_number": 1,
        "waiting_round":0,
        "waiting_round_end_action":[
        ],        
        "method_settlement": "",
        "auto_begin": 0,
        "auto_result": 0,
        "location": "结局:1", 
        "type":"END",
        "icon": "rite_ex_2", 
        "tag_tips": [  
        ],
        "tag_tips_up":{
        },
        "tips_text":[
            "你需要设法收集或者升级那些可以否定苏丹的思潮",
            "最差的情况下，你可以用金色的征服卡来挑战苏丹",
            "谨慎选择思潮，这会成为新国家诞生的理由，不可更改"
        ],
        "open_conditions": [
            {
                "condition": {
                    "s10.rare=":4
                },
                "tips": "至少需要黄金品级的思潮或征服卡"
            }
        ],
        "random_text":{
        },
        "random_text_up":{        
        },
        "settlement_prior": [
        ],                
        "settlement": [
            {
                "condition": {
                    "!s10.is":2000911, //不是君权神授
                    "!s10.is":2000912, //不是昼夜契约
                },
                "result_title":"",
                "result_text": "你准备终结苏丹",
                "result": 
                {
                    "s10-可堆叠":1,
                    "s10+正当性":1,
                    "counter+7000325":1 //可以去拔承阳剑了
                },
                "action": {       
                    "rite":5010007
                }
            },
            {
                "condition": {
                    "s10.is":2000911, //君权神授
                },
                "result_title":"",
                "result_text": "以神的名义，我将是你们新得苏丹",
                "result": 
                {
                },
                "action": {         //直接导向最终结局，中间不用打了
                }
            },
            {
                "condition": {
                    "s10.is":2000912, //昼夜契约
                },
                "result_title":"",
                "result_text": "你们都将获得新生",
                "result": 
                {
                },
                "action": {         //直接导向最终结局，中间不用打了
                }
            }
        ],               
        "settlement_extre": [
        ],
        "cards_slot":
        {
            "s1":
                {
                    "condition": 
                    {
                        "type":"item",
                        "is":2000901, //2级
                        "苏丹的精兵":1
                    },
                    "open_adsorb":1,
                    "is_key":0,
                    "is_empty":0,
                    "is_enemy":0, 
                    "text":"苏丹的军队"
                },
            "s2":
            {
                "condition": 
                {
                    "type":"item",
                    "is":2000902, //3级
                    "苏丹的精兵":1
                },
                "open_adsorb":1,
                "is_key":0,
                "is_empty":0,
                "is_enemy":0, 
                "text":"苏丹的军队"
            },
            "s3":
            {
                "condition": 
                {
                    "type":"item",
                    "is":2000903, //4级
                    "苏丹的精兵":1
                },
                "open_adsorb":1,
                "is_key":0,
                "is_empty":0,
                "is_enemy":0, 
                "text":"苏丹的军队"
            },
            "s4":
            {
                "condition": 
                {
                    "type":"item",
                    "is":2000904, //3级
                    "苏丹的精兵":1
                },
                "open_adsorb":1,
                "is_key":0,
                "is_empty":0,
                "is_enemy":0, 
                "text":"苏丹的军队"
            },
            "s5":
            {
                "condition": 
                {
                    "type":"item",
                    "is":2000905,//2级
                    "苏丹的精兵":1
                },
                "open_adsorb":1,
                "is_key":0,
                "is_empty":0,
                "is_enemy":0, 
                "text":"苏丹的军队"
            },
            "s6":
            {
                "condition": 
                {
                    "type":"item",
                    "is":2000906, //2级
                    "苏丹的精兵":1
                },
                "open_adsorb":1,
                "is_key":0,
                "is_empty":0,
                "is_enemy":0, 
                "text":"苏丹的军队"
            },
            "s7":
            {
                "condition": 
                {
                    "type":"item",
                    "is":2000907, //4级
                    "苏丹的精兵":1
                },
                "open_adsorb":1,
                "is_key":0,
                "is_empty":0,
                "is_enemy":0, 
                "text":"苏丹的军队"
            },
            "s8":
            {
                "condition": 
                {
                    "type":"item",
                    "is":2000908, //3级
                    "苏丹的精兵":1
                },
                "open_adsorb":1,
                "is_key":0,
                "is_empty":0,
                "is_enemy":0, 
                "text":"苏丹的军队"
            },
            "s9":
            {
                "condition": 
                {
                    "type":"item",
                    "is":2000909, //4级
                    "苏丹的精兵":1
                },
                "open_adsorb":1,
                "is_key":0,
                "is_empty":0,
                "is_enemy":0, 
                "text":"苏丹的军队"
            },
            "s10":
            {
                "condition": 
                {
                    "any":{
                        "all":{
                            "is":2000172, //弑君的计划
                            "cost.思潮":1
                        },
                        "is":2000910, //革命的计划
                        "is":2000911, //君权神授
                        "is":2000912, //昼夜契约
                        "all":{
                            "is":2000913, //誓言之证
                            "rare":4
                        },
                        "is":2010016, //金征服
                    }

                },
                "open_adsorb":0,
                "is_key":0,
                "is_empty":0,
                "is_enemy":0, 
                "text":"你的决心。至少黄金品级的谋反理念或征服卡"
            }
        }
    } 