 {
        "id": 5003005,
        "name": "积郁成疾",
        "text": "你发现梅姬最近夜间迟迟无法入眠，白天也提不起精神来，像是生病了。",       
        "tips": "",
        "mapping_id":8001077,   
        "once_new":0,
        "round_number": 3,
        "waiting_round":0,
        "waiting_round_end_action":[
        ],        
        "method_settlement": "",
        "auto_begin": 1,
        "auto_result": 0,
        "location": "自宅:[2,12]", 
        "icon": "rite_20", 
        "tag_tips": [   
        ],
        "tag_tips_up":{
        },
        "tips_text":[
            "忧郁与疾病会永久性降低妻子的属性",
            "如果妻子反复生病，你可能会失去她"
        ],
        "open_conditions": [
        ],
        "random_text":{
        },
        "random_text_up":{
        },
        "settlement_prior": [
        ],                
        "settlement": [
            {
                "condition": {
                    "s1.抑郁>=":3
                },
                "result_title":"",
                "result_text": "在你的劝说下，梅姬勉强吃了点东西，但很快又抑制不住地吐了。你几乎是眼睁睁地看着她变得苍白、衰弱、枯槁。她时常发呆，无故落泪；她总是被噩梦惊醒，然后整夜难眠。终于有一天，你起床时发现她竟难得地还在睡着，安恬得像一个婴儿。\n这天天气很好，仆人们忙碌着布置早餐的餐桌，宅院里一片熙攘的热闹。这片虚浮的繁荣轻轻包裹着一颗寂静的、忧郁的、停止跳动的心脏。你握住她冰凉的双手，一再确认，你已永远地失去了梅姬。",
                "result": 
                {
                    "clean.s1":1  
                },
                "action": {
                }
            },
            {
                "condition": {
                    "s1.抑郁<":3
                },
                "result_title":"",
                "result_text": "在你的劝说之下，梅姬终于勉强吃了点东西，但忧郁的阴云依然密布在她轻轻蹙起的眉间。她需要的不是食物、毛毯或者药剂，就像一株髓芯朽坏的树，阳光和雨露已经无法令它继续如常地生存。她需要的是某种无形无质之物——它令人生，亦令人死；它有多令人快活，就有多令人煎熬。",
                "result": 
                {      
                    "s1+抑郁":1, //添加抑郁标签
                    "s1-魅力":1, 
                    "s1-智慧":1, 
                    "s1-社交":1 
                },
                "action": {
                }
            }
        ],               
        "settlement_extre": [
        ],
        "cards_slot":
        {
            "s1":
                {
                    "condition": 
                    {
                        "妻子":1,
                        "type":"char"
                    },
                    "open_adsorb":1,
                    "is_key":0,
                    "is_empty":0,
                    "is_enemy":1,
                    "text":"妻子生病了。"
                }
        }
    } 