 {
        "id": 5006524,
        "name": "受赏",
        "text": "你有权决定让谁来接受那份来自宫廷的赏赐，尽管它写明了是赠予鲁梅拉的。",       
        "tips": "",
        "mapping_id":8001246,
        "once_new":1,
        "round_number": 1,
        "waiting_round":0,
        "waiting_round_end_action":[
        ],        
        "method_settlement": "",
        "auto_begin": 0, 
        "auto_result": 0,
        "location": "自宅:[2,12]", 
        "icon": "rite_1", 
        "tag_tips": [        
        ],
        "tag_tips_up":{
        },
        "tips_text":[
        ],
        "open_conditions": [
        ],
        "random_text":{
        },
        "random_text_up":{
        },
        "settlement_prior": [
        ],                
        "settlement": [
            {
                "condition": {
                    "s1.is":2000123 //是鲁梅拉
                },
                "result_title":"",
                "result_text": "你告诉鲁梅拉，这是宫里赐给她的东西，也是她应得的。女孩眼睛里闪烁着明亮的光辉，在确认你不是要把她赶走之后，大着胆子把那些华贵的衣料比在自己身上，似乎在估量它的价值。你微笑地看着她，估计过不了几天，这些赏赐就都会变成书本吧？",
                "result": 
                {
                    "s1+智慧":3 
                },
                "action": {
                }
            },
            {
                "condition": {
                    "s1.妻子":1, //是梅姬
                    "s2":1 //有妻子的不满
                },
                "result_title":"",
                "result_text": "你把这些奢华而又美丽的宝物带到梅姬的面前，告诉她，这是送给她的。梅姬高兴极了，不光是因为这些漂亮精致的绸缎格外讨人喜欢，更因为你第一个想到了她。她毫不吝啬地给了你一个热吻，曾经横亘于你们之间的芥蒂，仿佛也淡了许多。",
                "result": 
                {
                    "s1+魅力":1,
                    "clean.s2":1  
                },
                "action": {
                }
            },
            {
                "condition": {
                    "s1.妻子":1 //是梅姬
                },
                "result_title":"",
                "result_text": "你把这些奢华而又美丽的宝物带到梅姬的面前，告诉她，这是送给她的。梅姬高兴极了，不光是因为这些东西格外讨人喜欢，更因为你第一个想到了她。她毫不吝啬地给了你一个热吻，你被她亲得飘飘然如在云端。从未有这一刻比现在更令你觉得，这些漂亮的锦缎和珠宝和梅姬是如此相配。",
                "result": 
                {
                    "s1+魅力":2 
                },
                "action": {
                }
            },
            {
                "condition": {
                    "s1.主角":1 //是自己
                },
                "result_title":"",
                "result_text": "你是鲁梅拉的主人，你有权决定这些东西的归属。那些漂亮的布匹就先典为金币，至于那枚漂亮的臂环，你留下自有用处。",
                "result": 
                {
                    "coin":5,
                    "card":[2000553,"已拥有+1"] //纯金臂环
                },
                "action": {
                }
            },
            {
                "condition": {
                },
                "result_title":"",
                "result_text": "你偷偷把这些奢华而又美丽的宝物送给了[s1.name]，有些这些东西的装点，[s1.gender]变得更富有魅力。\n可是，宫里赏赐了东西这件事是瞒不住的，得知此事后，梅姬好几天没有理你。扪心自问，你的心里还有这个家的女主人吗？",
                "result": 
                {
                    "s1+魅力":1,
                    // "card":2000083 //妻子的不满  
                },
                "action": {
                }
            }
        ],               
        "settlement_extre": [
        ],
        "cards_slot":
        {
            "s1":
                {
                    "condition": 
                    {
                        "type":"char"
                    },
                    "open_adsorb":0,
                    "is_key":0,
                    "is_empty":0,
                    "is_enemy":0,
                    "text":"你决定选谁来领受这份恩赐？"
                },
            "s2":
            {
                "condition": 
                {
                    "type":"item",
                    "is":2000083,
                    "cost.不满":1
                },
                "open_adsorb":0,
                "is_key":0,
                "is_empty":1,
                "is_enemy":0,
                "text":"如果让梅姬领受这份恩赐，可以借机消除一张妻子的不满"
            }
        }
    } 