{
    "id": 5008053,
    "name": "失踪的快脚",
    "text": "失踪的快脚",       
    "tips": "",
    "mapping_id":8001140,
    "once_new":0,
    "round_number": 3,
    "waiting_round":1,
    "waiting_round_end_action":[
    ],
    "method_settlement": "",
    "auto_begin": 1,
    "auto_result":0,
    "location": "自宅:[2,12]", 
    "icon": "rite_8", 
    "tag_tips": [
    ],
    "tag_tips_up":{
    },
    "tips_text":[

    ],
    "open_conditions": [
    
    ],
    "random_text":{
    },
    "random_text_up":{
    },
    "settlement_prior": [
    
    ],                
    "settlement": [
        
        {
            "condition":
            {
                "s1":1
            },
            "result_title":"快脚回家了",
            "result_text": "他们走了，过了很久以后，只有快脚回来了。你们都没再提起阿鲁米娜这个人。",
            "result": 
            {        

            },
            "action":
            {
                
            }
        }
    ],                
    "settlement_extre": [
       
    ],
    "cards_slot":
    {
        "s1":
        {
            "condition": 
            {
                "type":"char",
                "is":2000370
            },
            "open_adsorb":1,
            "is_key":0,
            "is_empty":0,
            "is_enemy":0,
            "text":"快脚" 
        }
    }
} 