 {
        "id": 5008105,
        "name": "颂神会",
        "text": "祭司伊曼差人给你送来了一封感谢信，措辞非常官方、书面，文字都是用金粉写下的，大概意思就是说希望召开一次颂神会，而这个“神圣的恩赐”就这样掉到了你头上。",       
        "tips": "",
        "mapping_id":8001141,
        "once_new":0,
        "round_number": 3, //立即执行
        "waiting_round":3,
        "waiting_round_end_action":[
        ],        
        "method_settlement": "",
        "auto_begin": 0,  //自动执行
        "auto_result": 0, 
        "location": "商业区:[10,19]",
        "icon": "rite_18",  
        "tag_tips": [
        ],
        "tag_tips_up":{
            "tips":["体魄"]
        },        
        "tips_text":[
            "帮忙干活的人需要强健的体魄，不低于10点",
            "需要放入十金币"
        ],
        "open_conditions": [
            {
                "condition": {
                    "any":{
                        "s5":1,
                        "s3":1,
                        "s4":1
                    },
                    "f:主角<":2, 
                    "f:体魄>=":10  
                },
                "tips": "需要派人去参加"
            }
        ],
        "random_text":{
        },
        "random_text_up":{
        },
        "settlement_prior": [
        ],                
        "settlement": [
           
        ],               
        "settlement_extre": [
            {
                "condition": {

                       "s2":1
                },
                "result_title":"",
                "result_text": "在祭司们的带领下，人们高唱纯净之神的颂歌，一系列复杂考究的仪式之后，黑街所有的乞丐、妓女、小偷、流浪儿都短暂地沐浴在神光中，成为最虔诚的信徒，净化了部分他们生而为人的原罪。\n当然，祭司们满意地离开之后的第二天，他们就又重新是乞丐、妓女、小偷、流浪儿了，因为今天没有人为他们发放免费的圣餐饼。",
                "result": 
                {     
                    
                "s1+体魄":1,
                "s3+体魄":1,   
                "s4+体魄":1,
                "s5+体魄":1,    //给参与者（包括哈比卜）体魄+1
                "counter+7100003":1, //权势+1
                "counter+7100001":1, //善名+1
                 "s6+虔信":1
                },
                "action": {

                    "counter+7000538":1 //哈比卜宴会触发次数计数器+1
                    
                  
           
                }
            }

        ],
        "cards_slot":
        {
            "s1":
            {
                "condition": 
                {
                    "type":"char",
                    "is":2000014
                },
                "open_adsorb":0,
                "is_key":0,
                "is_empty":0,
                "is_enemy":0,
                "text":"宴会主厨"
            },
            "s2":
            {
                "condition": 
                {
                    "type":"item",
                    "cost.金币":10
                },
                "open_adsorb":0,
                "is_key":0,
                "is_empty":0,
                "is_enemy":0,
                "text":"本次颂神会需要你出10枚金币筹办"
            },
            "s3":
            {
                "condition": 
                {
                    "type":"char"
                  
                },
                "open_adsorb":0,
                "is_key":0,
                "is_empty":1,
                "is_enemy":0,
                "text":"你可以请一位朋友来帮忙"
            },
            "s4":
            {
                "condition": 
                {
                    "type":"char"
              
                },
                "open_adsorb":0,
                "is_key":0,
                "is_empty":1,
                "is_enemy":0,
                "text":"你可以请一位朋友来帮忙"
            },
            "s5":
            {
                "condition": 
                {
                    "type":"char"
                 
                },
                "open_adsorb":0,
                "is_key":0,
                "is_empty":1,
                "is_enemy":0,
                "text":"你可以请一位朋友来帮忙"
            },
            "s6":
            {
                "condition": 
                {
                    "type":"item",
                    "any":{
                        "is":2000726,
                        "is":2000727,
                        "is":2000728
                    }                    
                },
                "open_adsorb":1,
                "is_key":0,
                "is_empty":0,
                "is_enemy":0,
                "text":"你对纯净之神的信仰"
            }
        }
    } 