{
    "id": 6000019,
    "name": "普通妓院loot",
    "repeat": 1,
    "type": 2, 
    "item": [
        {
            "condition":{
                "table_have.2000080":1,
                "table_have.2000080.妓女": 1
            },
            "num" : "1",
            "id" : "5002003",
            "type" : "rite",
            "weight" : 60
        },
        {
            "condition":{
                "table_have.2000081": 1,
                "table_have.2000081.妓女": 1
            },
            "num" : "1",
            "id" : "5002004",
            "type" : "rite",
            "weight" : 60
        },
        {
            "condition":{
                "table_have.2000082": 1,
                "table_have.2000082.妓女": 1
            },
            "num" : "1",
            "id" : "5002005",
            "type" : "rite",
            "weight" : 60
        },
        {
            "condition":{
                "all":{
                    "table_have.2000772":1,
                    "table_have.2000772.妓女>=": 1,
                    "counter.7000313>=":1
                }
            },
            "num" : "1",
            "id" : "5002035",
            "type" : "rite",
            "weight" : 60
        }
    ]
}