{
    "id": 6001070,
    "name": "孩子们(重复",
    "repeat": 1,
    "type": 2, // 2 普通权重, 3 维新
    "item": [
        {
            "num" : "1",
            "id" : "5321189",   //做鸡
            "type" : "event",
            "weight" : 60
        },
        {
            "condition":{
                
                "have.2000005":1 //异国商人存活
                 
            },
            "num" : "1",
            "id" : "5321190",    //做牛马，需要异国商人存活
            "type" : "event",
            "weight" : 60
        },
        {
            "num" : "1",
            "id" : "5321191",      //做羔羊（正
            "type" : "event",
            "weight" : 60
        },
        {
            "num" : "1",
            "id" : "5321192",           //做狗
            "type" : "event",
            "weight" : 60
        },
        {
            "condition":{
                
                "have.2000022":1, //邪术师存活
                "counter.7000011>=":1  //用来标识已经完成和邪术师接触
                 
            },
            "num" : "1",
            "id" : "5321193",           //做羔羊（密）
            "type" : "event",
            "weight" : 60
        },
        {
            "condition":{
                
                "have.2000113":1 //阿里木存活
                 
            },
            "num" : "1",
            "id" : "5321194",          //做老鼠，需要阿里木存活
            "type" : "event",
            "weight" : 60
        },
        {
            "condition":{
                
                "counter.7000379<":1,   //场上没有孤儿院
                "have.2000113":1 //阿里木存活
                 
            },
            "num" : "1",
            "id" : "5321195",        //做人
            "type" : "event",
            "weight" : 60
        }
    ]
}